{
  "about": [
    {
      "type": "text",
      "value": "<a href=\"https://www.youtube.com/watch?v=Yw6u6YkTgQ4\">hello, world</a>"
    }
  ],
  "work": [
    {
      "type": "image",
      "value": {
        "slug": "torcoes-1.jpg",
        "caption": "Torções, 2020"
      }
    },
    {
      "type": "image",
      "value": {
        "slug": "torcoes-2.jpg",
        "caption": "Torções, 2020"
      }
    },
    {
      "type": "image",
      "value": {
        "slug": "torcoes-3.jpg",
        "caption": "Torções, 2020"
      }
    },
    {
      "type": "image",
      "value": {
        "slug": "torcoes-7.jpg",
        "caption": "Torções, 2020"
      }
    },
    {
      "type": "image",
      "value": {
        "slug": "torcoes-9.jpg",
        "caption": "Torções, 2020"
      }
    },
    {
      "type": "image",
      "value": {
        "slug": "torcoes-10.jpg",
        "caption": "Torções, 2020"
      }
    }
  ],
  "slug": "outros-projetos-21.jpg",
  "caption": "Tk tk tk título, tk ano"
}